lib.v
module pg(start,tc,q,clk,reset);
  input start,tc,clk,reset;
  output  q;
    
  wire t1,t2;
  parameter vdd=1'b1;
  parameter gnd=1'b0;

  mux2 M1(t2, vdd, start, q);
  mux2 M2(q, gnd, tc, t1);
  dfr d2(clk, reset, t1, t2);
endmodule

module reg4(input wire clk, en, input wire [3:0] a, output wire [3:0] y);
  dfl dfl_1(clk, en, a[0], y[0]);
  dfl dfl_2(clk, en, a[1], y[1]);
  dfl dfl_3(clk, en, a[2], y[2]);
  dfl dfl_4(clk, en, a[3], y[3]);
endmodule

module reg8(input wire clk,start,ld,cy,input wire [3:0]c,b,output wire [8:0] p);
  wire en2;
  dfl dfl_1(clk, ld, cy, p[8]);
  dfl dfl_2(clk, ld, c[3], p[7]);
  dfl dfl_3(clk, ld, c[2], p[6]);
  dfl dfl_4(clk, ld, c[1], p[5]);
  dfl dfl_5(clk, ld, c[0], p[4]);

  // module mux_df(input wire clk, i0, i1, s, load, output wire z_);
  mux_df muxdf_0(clk, p[4], b[3], start, en2, p[3]);
  mux_df muxdf_1(clk, p[3], b[2], start, en2, p[2]);
  mux_df muxdf_2(clk, p[2], b[1], start, en2, p[1]);
  mux_df muxdf_3(clk, p[1], b[0], start, en2, p[0]);

assign en2 = start | ld;
endmodule

module cnt4(out, data, load, en, clk, tc, lmt);
  output [1:0] out;
  output reg tc;
  input [1:0] data;
  input load, en, clk;
  reg [1:0] out;
  parameter reset=0;
  input [1:0]lmt;
  initial begin out=2'b00; tc=0; end
  always @(posedge clk)
  if (reset) begin out <= 2'b00 ; end 
  else if (load) begin out <= data; end 
  else if (en) out <= out + 2'b01;
  else out <= out;
  always @(posedge clk)
  if (out ==lmt) tc<=1;
  else tc<=0;
endmodule

// test modules for matching ddco lab
module mux2 (input wire i0, i1, j, output wire o);
  assign o = (j==0)?i0:i1;
endmodule

module invert (input wire i, output wire o);
   assign o = !i;
endmodule

module and2 (input wire i0, i1, output wire o);
  assign o = i0 & i1;
endmodule

module fulladd(input wire a,b,cin, output wire sum, cout);
    assign sum = a ^ b ^ cin;
    assign cout = (a&b)+(b&cin)+(cin&a);
endmodule

module mux_df(input wire clk, i0, i1, s, load, output wire z_);
  wire d_in;
  mux2 mux2_0(i0, i1, s, d_in);
  dfl dfl_0(clk, load, d_in, z_);
endmodule

module ripple_carry_4_bit(input wire [3:0] a,b, output wire [3:0] s, output wire cout);
  wire [2:0] c;
  fulladd f_0(a[0], b[0], 1'b0, s[0], c[0]);
  fulladd f_1(a[1], b[1], c[0], s[1], c[1]);
  fulladd f_2(a[2], b[2], c[1], s[2], c[2]);
  fulladd f_3(a[3], b[3], c[2], s[3], cout);
endmodule

module df (input wire clk, in, output wire out);
  reg df_out;
  initial begin df_out = 0; end
  always@(posedge clk) df_out <= in;
  assign out = df_out;
endmodule

module dfr (input wire clk, reset, in, output wire out);
  wire reset_, df_in;
  invert invert_0 (reset, reset_);
  and2 and2_0 (in, reset_, df_in);
  df df_0 (clk, df_in, out);
endmodule

module dfl(input wire clk, load, in, output wire out);
  wire _in;
  mux2 mux2_0(out, in, load, _in);
  df df_0 (clk, _in, out);
endmodule

module dfrl (input wire clk, reset, load, in, output wire out);
  wire _in;
  mux2 mux2_0(out, in, load, _in);
  dfr dfr_1(clk, reset, _in, out);
endmodule

seq_mul.v
`timescale 1ns / 1ps
module seq_mul(clk,start,a,b,op);
    input [3:0] a,b;
    input clk,start;
    output [7:0] op;

    wire [8:0] p;
    wire [3:0] t,c,a1;
    wire ld,load,shift,cy;
    wire [1:0] out;

    reg4 rg1(clk, start, a, a1);

    assign t[0] = a1[0] & p[0]; 
    assign t[1] = a1[1] & p[0];
    assign t[2] = a1[2] & p[0]; 
    assign t[3] = a1[3] & p[0];

    ripple_carry_4_bit ad(p[8:5], t, c, cy);

    reg8 rg2(clk, start, ld, cy, c, b, p);

    cnt4 cnt(out, 2'b00, load, en, clk, tc, 2'b10);
    pg pg1(start, tc, en, clk, 1'b0);

    assign load = start | tc;
    assign ld = en;
    assign op = p[8:1];
endmodule

seq_mul_tb.v
`timescale 1ns / 100ps
module seq_mul_tb;

	// Inputs
	reg clk;
	reg start;
	reg [3:0] a;
	reg [3:0] b;

   wire [7:0] op;
	initial begin $dumpfile("tb.vcd"); $dumpvars(0,seq_mul_tb); end
	seq_mul uut (
		.clk(clk), 
		.start(start), 
		.a(a), 
		.b(b),
		.op(op)
	);

always #10 clk = ~clk;
	initial begin
		clk = 0;
		start = 0;
		a = 0;
		b = 0;

		//reset
		#109.5;
        start = 1;
		  a = 4'b0101;
		b = 4'b1001;
		#20;
		start = 0;
		  a = 0;
		b = 0;
		// #100 $finish;
	end
	initial begin
		clk = 0;
		start = 0;
		a = 0;
		b = 0;

		//reset
		#109.5;
        start = 1;
		  a = 4'b1101;
		b = 4'b0101;
		#20;
		start = 0;
		  a = 0;
		b = 0;
		#100 $finish;
	end
		// #150;
		// start = 1;
		//   a = 4'b0101;
		// b = 4'b0011;
		// #20;
		// start = 0;
		//   a = 0;
		// b = 0;

		// #150;
		// start = 1;
		//   a = 4'b1001;
		// b = 4'b0101;
		// #20;
		// start = 0;
		//   a = 0;
		// b = 0;
	// 	#100 $finish;
	// end
      
endmodule

tb.vcd
$date
	Sun Nov 21 14:50:18 2021
$end
$version
	Icarus Verilog
$end
$timescale
	1ps
$end
$scope module seq_mul_tb $end
$var wire 8 ! op [7:0] $end
$var reg 4 " a [3:0] $end
$var reg 4 # b [3:0] $end
$var reg 1 $ clk $end
$var reg 1 % start $end
$scope module uut $end
$var wire 4 & a [3:0] $end
$var wire 4 ' b [3:0] $end
$var wire 1 $ clk $end
$var wire 1 ( ld $end
$var wire 1 ) load $end
$var wire 1 % start $end
$var wire 1 * tc $end
$var wire 4 + t [3:0] $end
$var wire 9 , p [8:0] $end
$var wire 2 - out [1:0] $end
$var wire 8 . op [7:0] $end
$var wire 1 / en $end
$var wire 1 0 cy $end
$var wire 4 1 c [3:0] $end
$var wire 4 2 a1 [3:0] $end
$scope module ad $end
$var wire 4 3 a [3:0] $end
$var wire 4 4 b [3:0] $end
$var wire 4 5 s [3:0] $end
$var wire 1 0 cout $end
$var wire 3 6 c [2:0] $end
$scope module f_0 $end
$var wire 1 7 a $end
$var wire 1 8 b $end
$var wire 1 9 cin $end
$var wire 1 : sum $end
$var wire 1 ; cout $end
$upscope $end
$scope module f_1 $end
$var wire 1 < a $end
$var wire 1 = b $end
$var wire 1 > cin $end
$var wire 1 ? sum $end
$var wire 1 @ cout $end
$upscope $end
$scope module f_2 $end
$var wire 1 A a $end
$var wire 1 B b $end
$var wire 1 C cin $end
$var wire 1 D sum $end
$var wire 1 E cout $end
$upscope $end
$scope module f_3 $end
$var wire 1 F a $end
$var wire 1 G b $end
$var wire 1 H cin $end
$var wire 1 I sum $end
$var wire 1 0 cout $end
$upscope $end
$upscope $end
$scope module cnt $end
$var wire 1 $ clk $end
$var wire 2 J data [1:0] $end
$var wire 2 K lmt [1:0] $end
$var wire 1 ) load $end
$var wire 1 / en $end
$var reg 2 L out [1:0] $end
$var reg 1 * tc $end
$upscope $end
$scope module pg1 $end
$var wire 1 $ clk $end
$var wire 1 M reset $end
$var wire 1 % start $end
$var wire 1 * tc $end
$var wire 1 N t2 $end
$var wire 1 O t1 $end
$var wire 1 / q $end
$scope module M1 $end
$var wire 1 P i1 $end
$var wire 1 % j $end
$var wire 1 / o $end
$var wire 1 N i0 $end
$upscope $end
$scope module M2 $end
$var wire 1 / i0 $end
$var wire 1 Q i1 $end
$var wire 1 * j $end
$var wire 1 O o $end
$upscope $end
$scope module d2 $end
$var wire 1 $ clk $end
$var wire 1 O in $end
$var wire 1 M reset $end
$var wire 1 R reset_ $end
$var wire 1 N out $end
$var wire 1 S df_in $end
$scope module and2_0 $end
$var wire 1 O i0 $end
$var wire 1 S o $end
$var wire 1 R i1 $end
$upscope $end
$scope module df_0 $end
$var wire 1 $ clk $end
$var wire 1 S in $end
$var wire 1 N out $end
$var reg 1 N df_out $end
$upscope $end
$scope module invert_0 $end
$var wire 1 M i $end
$var wire 1 R o $end
$upscope $end
$upscope $end
$upscope $end
$scope module rg1 $end
$var wire 4 T a [3:0] $end
$var wire 1 $ clk $end
$var wire 1 % en $end
$var wire 4 U y [3:0] $end
$scope module dfl_1 $end
$var wire 1 $ clk $end
$var wire 1 V in $end
$var wire 1 % load $end
$var wire 1 W out $end
$var wire 1 X _in $end
$scope module df_0 $end
$var wire 1 $ clk $end
$var wire 1 W out $end
$var wire 1 X in $end
$var reg 1 W df_out $end
$upscope $end
$scope module mux2_0 $end
$var wire 1 W i0 $end
$var wire 1 V i1 $end
$var wire 1 % j $end
$var wire 1 X o $end
$upscope $end
$upscope $end
$scope module dfl_2 $end
$var wire 1 $ clk $end
$var wire 1 Y in $end
$var wire 1 % load $end
$var wire 1 Z out $end
$var wire 1 [ _in $end
$scope module df_0 $end
$var wire 1 $ clk $end
$var wire 1 Z out $end
$var wire 1 [ in $end
$var reg 1 Z df_out $end
$upscope $end
$scope module mux2_0 $end
$var wire 1 Z i0 $end
$var wire 1 Y i1 $end
$var wire 1 % j $end
$var wire 1 [ o $end
$upscope $end
$upscope $end
$scope module dfl_3 $end
$var wire 1 $ clk $end
$var wire 1 \ in $end
$var wire 1 % load $end
$var wire 1 ] out $end
$var wire 1 ^ _in $end
$scope module df_0 $end
$var wire 1 $ clk $end
$var wire 1 ] out $end
$var wire 1 ^ in $end
$var reg 1 ] df_out $end
$upscope $end
$scope module mux2_0 $end
$var wire 1 ] i0 $end
$var wire 1 \ i1 $end
$var wire 1 % j $end
$var wire 1 ^ o $end
$upscope $end
$upscope $end
$scope module dfl_4 $end
$var wire 1 $ clk $end
$var wire 1 _ in $end
$var wire 1 % load $end
$var wire 1 ` out $end
$var wire 1 a _in $end
$scope module df_0 $end
$var wire 1 $ clk $end
$var wire 1 ` out $end
$var wire 1 a in $end
$var reg 1 ` df_out $end
$upscope $end
$scope module mux2_0 $end
$var wire 1 ` i0 $end
$var wire 1 _ i1 $end
$var wire 1 % j $end
$var wire 1 a o $end
$upscope $end
$upscope $end
$upscope $end
$scope module rg2 $end
$var wire 4 b b [3:0] $end
$var wire 4 c c [3:0] $end
$var wire 1 $ clk $end
$var wire 1 0 cy $end
$var wire 1 d en2 $end
$var wire 1 ( ld $end
$var wire 1 % start $end
$var wire 9 e p [8:0] $end
$scope module dfl_1 $end
$var wire 1 $ clk $end
$var wire 1 0 in $end
$var wire 1 ( load $end
$var wire 1 f out $end
$var wire 1 g _in $end
$scope module df_0 $end
$var wire 1 $ clk $end
$var wire 1 f out $end
$var wire 1 g in $end
$var reg 1 f df_out $end
$upscope $end
$scope module mux2_0 $end
$var wire 1 f i0 $end
$var wire 1 0 i1 $end
$var wire 1 ( j $end
$var wire 1 g o $end
$upscope $end
$upscope $end
$scope module dfl_2 $end
$var wire 1 $ clk $end
$var wire 1 h in $end
$var wire 1 ( load $end
$var wire 1 i out $end
$var wire 1 j _in $end
$scope module df_0 $end
$var wire 1 $ clk $end
$var wire 1 i out $end
$var wire 1 j in $end
$var reg 1 i df_out $end
$upscope $end
$scope module mux2_0 $end
$var wire 1 i i0 $end
$var wire 1 h i1 $end
$var wire 1 ( j $end
$var wire 1 j o $end
$upscope $end
$upscope $end
$scope module dfl_3 $end
$var wire 1 $ clk $end
$var wire 1 k in $end
$var wire 1 ( load $end
$var wire 1 l out $end
$var wire 1 m _in $end
$scope module df_0 $end
$var wire 1 $ clk $end
$var wire 1 l out $end
$var wire 1 m in $end
$var reg 1 l df_out $end
$upscope $end
$scope module mux2_0 $end
$var wire 1 l i0 $end
$var wire 1 k i1 $end
$var wire 1 ( j $end
$var wire 1 m o $end
$upscope $end
$upscope $end
$scope module dfl_4 $end
$var wire 1 $ clk $end
$var wire 1 n in $end
$var wire 1 ( load $end
$var wire 1 o out $end
$var wire 1 p _in $end
$scope module df_0 $end
$var wire 1 $ clk $end
$var wire 1 o out $end
$var wire 1 p in $end
$var reg 1 o df_out $end
$upscope $end
$scope module mux2_0 $end
$var wire 1 o i0 $end
$var wire 1 n i1 $end
$var wire 1 ( j $end
$var wire 1 p o $end
$upscope $end
$upscope $end
$scope module dfl_5 $end
$var wire 1 $ clk $end
$var wire 1 q in $end
$var wire 1 ( load $end
$var wire 1 r out $end
$var wire 1 s _in $end
$scope module df_0 $end
$var wire 1 $ clk $end
$var wire 1 r out $end
$var wire 1 s in $end
$var reg 1 r df_out $end
$upscope $end
$scope module mux2_0 $end
$var wire 1 r i0 $end
$var wire 1 q i1 $end
$var wire 1 ( j $end
$var wire 1 s o $end
$upscope $end
$upscope $end
$scope module muxdf_0 $end
$var wire 1 $ clk $end
$var wire 1 t i0 $end
$var wire 1 u i1 $end
$var wire 1 d load $end
$var wire 1 % s $end
$var wire 1 v z_ $end
$var wire 1 w d_in $end
$scope module dfl_0 $end
$var wire 1 $ clk $end
$var wire 1 d load $end
$var wire 1 v out $end
$var wire 1 w in $end
$var wire 1 x _in $end
$scope module df_0 $end
$var wire 1 $ clk $end
$var wire 1 v out $end
$var wire 1 x in $end
$var reg 1 v df_out $end
$upscope $end
$scope module mux2_0 $end
$var wire 1 v i0 $end
$var wire 1 d j $end
$var wire 1 x o $end
$var wire 1 w i1 $end
$upscope $end
$upscope $end
$scope module mux2_0 $end
$var wire 1 t i0 $end
$var wire 1 u i1 $end
$var wire 1 % j $end
$var wire 1 w o $end
$upscope $end
$upscope $end
$scope module muxdf_1 $end
$var wire 1 $ clk $end
$var wire 1 y i0 $end
$var wire 1 z i1 $end
$var wire 1 d load $end
$var wire 1 % s $end
$var wire 1 { z_ $end
$var wire 1 | d_in $end
$scope module dfl_0 $end
$var wire 1 $ clk $end
$var wire 1 d load $end
$var wire 1 { out $end
$var wire 1 | in $end
$var wire 1 } _in $end
$scope module df_0 $end
$var wire 1 $ clk $end
$var wire 1 { out $end
$var wire 1 } in $end
$var reg 1 { df_out $end
$upscope $end
$scope module mux2_0 $end
$var wire 1 { i0 $end
$var wire 1 d j $end
$var wire 1 } o $end
$var wire 1 | i1 $end
$upscope $end
$upscope $end
$scope module mux2_0 $end
$var wire 1 y i0 $end
$var wire 1 z i1 $end
$var wire 1 % j $end
$var wire 1 | o $end
$upscope $end
$upscope $end
$scope module muxdf_2 $end
$var wire 1 $ clk $end
$var wire 1 ~ i0 $end
$var wire 1 !" i1 $end
$var wire 1 d load $end
$var wire 1 % s $end
$var wire 1 "" z_ $end
$var wire 1 #" d_in $end
$scope module dfl_0 $end
$var wire 1 $ clk $end
$var wire 1 d load $end
$var wire 1 "" out $end
$var wire 1 #" in $end
$var wire 1 $" _in $end
$scope module df_0 $end
$var wire 1 $ clk $end
$var wire 1 "" out $end
$var wire 1 $" in $end
$var reg 1 "" df_out $end
$upscope $end
$scope module mux2_0 $end
$var wire 1 "" i0 $end
$var wire 1 d j $end
$var wire 1 $" o $end
$var wire 1 #" i1 $end
$upscope $end
$upscope $end
$scope module mux2_0 $end
$var wire 1 ~ i0 $end
$var wire 1 !" i1 $end
$var wire 1 % j $end
$var wire 1 #" o $end
$upscope $end
$upscope $end
$scope module muxdf_3 $end
$var wire 1 $ clk $end
$var wire 1 %" i0 $end
$var wire 1 &" i1 $end
$var wire 1 d load $end
$var wire 1 % s $end
$var wire 1 '" z_ $end
$var wire 1 (" d_in $end
$scope module dfl_0 $end
$var wire 1 $ clk $end
$var wire 1 d load $end
$var wire 1 '" out $end
$var wire 1 (" in $end
$var wire 1 )" _in $end
$scope module df_0 $end
$var wire 1 $ clk $end
$var wire 1 '" out $end
$var wire 1 )" in $end
$var reg 1 '" df_out $end
$upscope $end
$scope module mux2_0 $end
$var wire 1 '" i0 $end
$var wire 1 d j $end
$var wire 1 )" o $end
$var wire 1 (" i1 $end
$upscope $end
$upscope $end
$scope module mux2_0 $end
$var wire 1 %" i0 $end
$var wire 1 &" i1 $end
$var wire 1 % j $end
$var wire 1 (" o $end
$upscope $end
$upscope $end
$upscope $end
$upscope $end
$upscope $end
$enddefinitions $end
#0
$dumpvars
0)"
0("
0'"
0&"
0%"
0$"
0#"
0""
0!"
0~
0}
0|
0{
0z
0y
0x
0w
0v
0u
0t
0s
0r
0q
0p
0o
0n
0m
0l
0k
0j
0i
0h
0g
0f
b0 e
0d
b0 c
b0 b
0a
0`
0_
0^
0]
0\
0[
0Z
0Y
0X
0W
0V
b0 U
b0 T
0S
1R
0Q
1P
0O
0N
0M
b0 L
b10 K
b0 J
0I
0H
0G
0F
0E
0D
0C
0B
0A
0@
0?
0>
0=
0<
0;
0:
09
08
07
b0 6
b0 5
b0 4
b0 3
b0 2
b0 1
00
0/
b0 .
b0 -
b0 ,
b0 +
0*
0)
0(
b0 '
b0 &
0%
0$
b0 #
b0 "
b0 !
$end
#10000
1$
#20000
0$
#30000
1$
#40000
0$
#50000
1$
#60000
0$
#70000
1$
#80000
0$
#90000
1$
#100000
0$
#109500
1}
1)"
1S
1|
1a
1("
1X
1^
1O
1z
1_
1&"
1V
1\
1)
1(
1/
1d
b101 #
b101 '
b101 b
b1101 "
b1101 &
b1101 T
1%
#110000
1j
1m
1s
1h
1k
1q
1I
1D
b1101 1
b1101 5
b1101 c
1:
1G
1B
18
b1101 +
b1101 4
1~
b10 !
b10 .
1N
1'"
b101 ,
b101 e
1{
1`
1]
b1101 2
b1101 U
1W
1$
#120000
0$
#129500
0}
1$"
0)"
0z
0&"
0V
0\
0_
0)
0|
1#"
0("
b0 #
b0 '
b0 b
b0 "
b0 &
b0 T
0%
#130000
0j
0s
1p
0h
0q
1n
0I
0:
b110 1
b110 5
b110 c
1?
1x
0$"
1)"
0G
0B
08
1<
1A
1w
0#"
1("
b0 +
b0 4
b110 3
1t
0~
1%"
b1101001 !
b1101001 .
1i
1l
1r
0{
1""
b11010010 ,
b11010010 e
0'"
b1 -
b1 L
1$
#140000
0$
#150000
1g
10
1H
0p
1E
0j
0n
1C
0h
0?
1@
0s
0m
0I
1>
0q
0k
b111 6
1;
0:
b0 1
b0 5
b0 c
0D
1G
1B
18
0)"
1}
0x
b1101 +
b1101 4
0("
1|
0w
17
0A
0%"
1y
0t
b110100 !
b110100 .
b11 3
b10 -
b10 L
1'"
0""
1v
0r
1o
b1101001 ,
b1101001 e
0i
1$
#160000
0$
#170000
1j
1h
0g
0p
1I
0n
0H
0>
b1000 1
b1000 5
b1000 c
0?
0C
0E
0;
b0 6
0@
00
0}
1$"
0G
0B
08
07
0<
1F
0|
1#"
b0 +
b0 4
0S
b1000 3
0y
1~
b10000010 !
b10000010 .
0O
1)
1f
0l
0o
0v
1{
b100000100 ,
b100000100 e
0'"
b11 -
b11 L
1*
1$
#180000
0$
#190000
1k
0h
1D
b100 1
b100 5
b100 c
0I
0d
0S
1("
0#"
1A
0F
0(
0/
0O
0)
1%"
0~
b1000001 !
b1000001 .
b100 3
0N
0*
b0 -
b0 L
1""
0{
1i
b10000010 ,
b10000010 e
0f
1$
