lib.v
module pg(input wire clk, reset, start, tc, output wire q);
  wire t1,t2;
  parameter vdd=1'b1;
  parameter gnd=1'b0;

  mux2 M1(t2, vdd, start, q);
  mux2 M2(q, gnd, tc, t1);
  dfr d2(clk, reset, t1, t2);
endmodule

module reg4(input wire clk, en, input wire [7:0] a, output wire [7:0] y);
  dfl dfl_1(clk, en, a[0], y[0]);
  dfl dfl_2(clk, en, a[1], y[1]);
  dfl dfl_3(clk, en, a[2], y[2]);
  dfl dfl_4(clk, en, a[3], y[3]);
  dfl dfl_5(clk, en, a[4], y[4]);
  dfl dfl_6(clk, en, a[5], y[5]);
  dfl dfl_7(clk, en, a[6], y[6]);
  dfl dfl_8(clk, en, a[7], y[7]);
endmodule

module reg8(input wire clk,start,ld,cy,input wire [7:0] c, b, output wire [16:0] p);
  wire en2;
  dfl dfl_0(clk, ld, cy, p[16]);

  dfl dfl_1(clk, ld, c[7], p[15]);
  dfl dfl_2(clk, ld, c[6], p[14]);
  dfl dfl_3(clk, ld, c[5], p[13]);
  dfl dfl_4(clk, ld, c[4], p[12]);
  dfl dfl_5(clk, ld, c[3], p[11]);
  dfl dfl_6(clk, ld, c[2], p[10]);
  dfl dfl_7(clk, ld, c[1], p[9]);
  dfl dfl_8(clk, ld, c[0], p[8]);

  // module mux_df(input wire clk, i0, i1, s, load, output wire z_);
  mux_df muxdf_0(clk, p[8], b[7], start, en2, p[7]);
  mux_df muxdf_1(clk, p[7], b[6], start, en2, p[6]);
  mux_df muxdf_2(clk, p[6], b[5], start, en2, p[5]);
  mux_df muxdf_3(clk, p[5], b[4], start, en2, p[4]);
  mux_df muxdf_4(clk, p[4], b[3], start, en2, p[3]);
  mux_df muxdf_5(clk, p[3], b[2], start, en2, p[2]);
  mux_df muxdf_6(clk, p[2], b[1], start, en2, p[1]);
  mux_df muxdf_7(clk, p[1], b[0], start, en2, p[0]);
  

assign en2 = start | ld;
endmodule

module cnt4(input wire clk, load, en, input wire [2:0] data, lmt, output reg tc, output reg [1:0] out);
  parameter reset=0;
  initial begin out=3'b000; tc=0; end
  always @(posedge clk)
  if (reset) begin out <= 3'b000 ; end 
  else if (load) begin out <= data; end 
  else if (en) out <= out + 3'b001;
  else out <= out;
  always @(posedge clk)
  if (out == lmt) tc <= 1;
  else tc<=0;
endmodule

// test modules for matching ddco lab
module mux2 (input wire i0, i1, j, output wire o);
  assign o = (j==0)?i0:i1;
endmodule

module invert (input wire i, output wire o);
   assign o = !i;
endmodule

module and2 (input wire i0, i1, output wire o);
  assign o = i0 & i1;
endmodule

module fulladd(input wire a,b,cin, output wire sum, cout);
    assign sum = a ^ b ^ cin;
    assign cout = (a&b)+(b&cin)+(cin&a);
endmodule

module mux_df(input wire clk, i0, i1, s, load, output wire z_);
  wire d_in;
  mux2 mux2_0(i0, i1, s, d_in);
  dfl dfl_0(clk, load, d_in, z_);
endmodule

module ripple_carry_4_bit(input wire [7:0] a,b, output wire [7:0] s, output wire cout);
  wire [6:0] c;
  fulladd f_0(a[0], b[0], 1'b0, s[0], c[0]);
  fulladd f_1(a[1], b[1], c[0], s[1], c[1]);
  fulladd f_2(a[2], b[2], c[1], s[2], c[2]);
  fulladd f_3(a[3], b[3], c[2], s[3], c[3]);
  fulladd f_4(a[4], b[4], c[3], s[4], c[4]);
  fulladd f_5(a[5], b[5], c[4], s[5], c[5]);
  fulladd f_6(a[6], b[6], c[5], s[6], c[6]);
  fulladd f_7(a[7], b[7], c[6], s[7], cout);
endmodule

module df (input wire clk, in, output wire out);
  reg df_out;
  initial begin df_out = 0; end
  always@(posedge clk) df_out <= in;
  assign out = df_out;
endmodule

module dfr (input wire clk, reset, in, output wire out);
  wire reset_, df_in;
  invert invert_0 (reset, reset_);
  and2 and2_0 (in, reset_, df_in);
  df df_0 (clk, df_in, out);
endmodule

module dfl(input wire clk, load, in, output wire out);
  wire _in;
  mux2 mux2_0(out, in, load, _in);
  df df_0 (clk, _in, out);
endmodule

module dfrl (input wire clk, reset, load, in, output wire out);
  wire _in;
  mux2 mux2_0(out, in, load, _in);
  dfr dfr_1(clk, reset, _in, out);
endmodule

seq_mul.v
`timescale 1ns / 1ps
module seq_mul(clk,start,a,b,op);
    input [7:0] a,b;
    input clk,start;
    output [15:0] op;

    wire [16:0] p;
    wire [7:0] t,c,a1;
    wire ld,load,shift,cy;
    wire [1:0] out;

    reg4 rg1(clk, start, a, a1);

    assign t[0] = a1[0] & p[0]; 
    assign t[1] = a1[1] & p[0];
    assign t[2] = a1[2] & p[0]; 
    assign t[3] = a1[3] & p[0];
    assign t[4] = a1[4] & p[0];
    assign t[5] = a1[5] & p[0];
    assign t[6] = a1[6] & p[0];
    assign t[7] = a1[7] & p[0];

    ripple_carry_4_bit ad(p[16:9], t, c, cy);

    reg8 rg2(clk, start, ld, cy, c, b, p);

    cnt4 cnt(clk, load, en, 3'b000, 3'b100, tc, out);
    pg pg1(clk, 1'b0, start, tc, en);

    assign load = start | tc;
    assign ld = en;
    assign op = p[16:1];
endmodule

seq_mul_tb.v
`timescale 1ns / 100ps
module seq_mul_tb;

	// Inputs
	reg clk;
	reg start;
	reg [7:0] a;
	reg [7:0] b;

   wire [15:0] op;
	initial begin $dumpfile("tb.vcd"); $dumpvars(0,seq_mul_tb); end
	seq_mul uut (
		.clk(clk), 
		.start(start), 
		.a(a), 
		.b(b),
		.op(op)
	);

always #10 clk = ~clk;
	initial begin
		clk = 0;
		start = 0;
		a = 0;
		b = 0;

		//reset
		#100;
        start = 1;
		a = 8'b01011101;
		b = 8'b10110101;
		#25;
		start = 0;
		a = 0;
		b = 0;
		#160 $finish;
	end
		// #150;
		// start = 1;
		//   a = 4'b0101;
		// b = 4'b0011;
		// #20;
		// start = 0;
		//   a = 0;
		// b = 0;

		// #150;
		// start = 1;
		//   a = 4'b1001;
		// b = 4'b0101;
		// #20;
		// start = 0;
		//   a = 0;
		// b = 0;
	// 	#100 $finish;
	// end
      
endmodule

tb.vcd
$date
	Sun Nov 21 18:17:29 2021
$end
$version
	Icarus Verilog
$end
$timescale
	1ps
$end
$scope module seq_mul_tb $end
$var wire 16 ! op [15:0] $end
$var reg 8 " a [7:0] $end
$var reg 8 # b [7:0] $end
$var reg 1 $ clk $end
$var reg 1 % start $end
$scope module uut $end
$var wire 8 & a [7:0] $end
$var wire 8 ' b [7:0] $end
$var wire 1 $ clk $end
$var wire 1 ( ld $end
$var wire 1 ) load $end
$var wire 1 % start $end
$var wire 1 * tc $end
$var wire 8 + t [7:0] $end
$var wire 17 , p [16:0] $end
$var wire 2 - out [1:0] $end
$var wire 16 . op [15:0] $end
$var wire 1 / en $end
$var wire 1 0 cy $end
$var wire 8 1 c [7:0] $end
$var wire 8 2 a1 [7:0] $end
$scope module ad $end
$var wire 8 3 a [7:0] $end
$var wire 8 4 b [7:0] $end
$var wire 8 5 s [7:0] $end
$var wire 1 0 cout $end
$var wire 7 6 c [6:0] $end
$scope module f_0 $end
$var wire 1 7 a $end
$var wire 1 8 b $end
$var wire 1 9 cin $end
$var wire 1 : sum $end
$var wire 1 ; cout $end
$upscope $end
$scope module f_1 $end
$var wire 1 < a $end
$var wire 1 = b $end
$var wire 1 > cin $end
$var wire 1 ? sum $end
$var wire 1 @ cout $end
$upscope $end
$scope module f_2 $end
$var wire 1 A a $end
$var wire 1 B b $end
$var wire 1 C cin $end
$var wire 1 D sum $end
$var wire 1 E cout $end
$upscope $end
$scope module f_3 $end
$var wire 1 F a $end
$var wire 1 G b $end
$var wire 1 H cin $end
$var wire 1 I sum $end
$var wire 1 J cout $end
$upscope $end
$scope module f_4 $end
$var wire 1 K a $end
$var wire 1 L b $end
$var wire 1 M cin $end
$var wire 1 N sum $end
$var wire 1 O cout $end
$upscope $end
$scope module f_5 $end
$var wire 1 P a $end
$var wire 1 Q b $end
$var wire 1 R cin $end
$var wire 1 S sum $end
$var wire 1 T cout $end
$upscope $end
$scope module f_6 $end
$var wire 1 U a $end
$var wire 1 V b $end
$var wire 1 W cin $end
$var wire 1 X sum $end
$var wire 1 Y cout $end
$upscope $end
$scope module f_7 $end
$var wire 1 Z a $end
$var wire 1 [ b $end
$var wire 1 \ cin $end
$var wire 1 ] sum $end
$var wire 1 0 cout $end
$upscope $end
$upscope $end
$scope module cnt $end
$var wire 1 $ clk $end
$var wire 3 ^ data [2:0] $end
$var wire 3 _ lmt [2:0] $end
$var wire 1 ) load $end
$var wire 1 / en $end
$var reg 2 ` out [1:0] $end
$var reg 1 * tc $end
$upscope $end
$scope module pg1 $end
$var wire 1 $ clk $end
$var wire 1 a reset $end
$var wire 1 % start $end
$var wire 1 * tc $end
$var wire 1 b t2 $end
$var wire 1 c t1 $end
$var wire 1 / q $end
$scope module M1 $end
$var wire 1 d i1 $end
$var wire 1 % j $end
$var wire 1 / o $end
$var wire 1 b i0 $end
$upscope $end
$scope module M2 $end
$var wire 1 / i0 $end
$var wire 1 e i1 $end
$var wire 1 * j $end
$var wire 1 c o $end
$upscope $end
$scope module d2 $end
$var wire 1 $ clk $end
$var wire 1 c in $end
$var wire 1 a reset $end
$var wire 1 f reset_ $end
$var wire 1 b out $end
$var wire 1 g df_in $end
$scope module and2_0 $end
$var wire 1 c i0 $end
$var wire 1 g o $end
$var wire 1 f i1 $end
$upscope $end
$scope module df_0 $end
$var wire 1 $ clk $end
$var wire 1 g in $end
$var wire 1 b out $end
$var reg 1 b df_out $end
$upscope $end
$scope module invert_0 $end
$var wire 1 a i $end
$var wire 1 f o $end
$upscope $end
$upscope $end
$upscope $end
$scope module rg1 $end
$var wire 8 h a [7:0] $end
$var wire 1 $ clk $end
$var wire 1 % en $end
$var wire 8 i y [7:0] $end
$scope module dfl_1 $end
$var wire 1 $ clk $end
$var wire 1 j in $end
$var wire 1 % load $end
$var wire 1 k out $end
$var wire 1 l _in $end
$scope module df_0 $end
$var wire 1 $ clk $end
$var wire 1 k out $end
$var wire 1 l in $end
$var reg 1 k df_out $end
$upscope $end
$scope module mux2_0 $end
$var wire 1 k i0 $end
$var wire 1 j i1 $end
$var wire 1 % j $end
$var wire 1 l o $end
$upscope $end
$upscope $end
$scope module dfl_2 $end
$var wire 1 $ clk $end
$var wire 1 m in $end
$var wire 1 % load $end
$var wire 1 n out $end
$var wire 1 o _in $end
$scope module df_0 $end
$var wire 1 $ clk $end
$var wire 1 n out $end
$var wire 1 o in $end
$var reg 1 n df_out $end
$upscope $end
$scope module mux2_0 $end
$var wire 1 n i0 $end
$var wire 1 m i1 $end
$var wire 1 % j $end
$var wire 1 o o $end
$upscope $end
$upscope $end
$scope module dfl_3 $end
$var wire 1 $ clk $end
$var wire 1 p in $end
$var wire 1 % load $end
$var wire 1 q out $end
$var wire 1 r _in $end
$scope module df_0 $end
$var wire 1 $ clk $end
$var wire 1 q out $end
$var wire 1 r in $end
$var reg 1 q df_out $end
$upscope $end
$scope module mux2_0 $end
$var wire 1 q i0 $end
$var wire 1 p i1 $end
$var wire 1 % j $end
$var wire 1 r o $end
$upscope $end
$upscope $end
$scope module dfl_4 $end
$var wire 1 $ clk $end
$var wire 1 s in $end
$var wire 1 % load $end
$var wire 1 t out $end
$var wire 1 u _in $end
$scope module df_0 $end
$var wire 1 $ clk $end
$var wire 1 t out $end
$var wire 1 u in $end
$var reg 1 t df_out $end
$upscope $end
$scope module mux2_0 $end
$var wire 1 t i0 $end
$var wire 1 s i1 $end
$var wire 1 % j $end
$var wire 1 u o $end
$upscope $end
$upscope $end
$scope module dfl_5 $end
$var wire 1 $ clk $end
$var wire 1 v in $end
$var wire 1 % load $end
$var wire 1 w out $end
$var wire 1 x _in $end
$scope module df_0 $end
$var wire 1 $ clk $end
$var wire 1 w out $end
$var wire 1 x in $end
$var reg 1 w df_out $end
$upscope $end
$scope module mux2_0 $end
$var wire 1 w i0 $end
$var wire 1 v i1 $end
$var wire 1 % j $end
$var wire 1 x o $end
$upscope $end
$upscope $end
$scope module dfl_6 $end
$var wire 1 $ clk $end
$var wire 1 y in $end
$var wire 1 % load $end
$var wire 1 z out $end
$var wire 1 { _in $end
$scope module df_0 $end
$var wire 1 $ clk $end
$var wire 1 z out $end
$var wire 1 { in $end
$var reg 1 z df_out $end
$upscope $end
$scope module mux2_0 $end
$var wire 1 z i0 $end
$var wire 1 y i1 $end
$var wire 1 % j $end
$var wire 1 { o $end
$upscope $end
$upscope $end
$scope module dfl_7 $end
$var wire 1 $ clk $end
$var wire 1 | in $end
$var wire 1 % load $end
$var wire 1 } out $end
$var wire 1 ~ _in $end
$scope module df_0 $end
$var wire 1 $ clk $end
$var wire 1 } out $end
$var wire 1 ~ in $end
$var reg 1 } df_out $end
$upscope $end
$scope module mux2_0 $end
$var wire 1 } i0 $end
$var wire 1 | i1 $end
$var wire 1 % j $end
$var wire 1 ~ o $end
$upscope $end
$upscope $end
$scope module dfl_8 $end
$var wire 1 $ clk $end
$var wire 1 !" in $end
$var wire 1 % load $end
$var wire 1 "" out $end
$var wire 1 #" _in $end
$scope module df_0 $end
$var wire 1 $ clk $end
$var wire 1 "" out $end
$var wire 1 #" in $end
$var reg 1 "" df_out $end
$upscope $end
$scope module mux2_0 $end
$var wire 1 "" i0 $end
$var wire 1 !" i1 $end
$var wire 1 % j $end
$var wire 1 #" o $end
$upscope $end
$upscope $end
$upscope $end
$scope module rg2 $end
$var wire 8 $" b [7:0] $end
$var wire 8 %" c [7:0] $end
$var wire 1 $ clk $end
$var wire 1 0 cy $end
$var wire 1 &" en2 $end
$var wire 1 ( ld $end
$var wire 1 % start $end
$var wire 17 '" p [16:0] $end
$scope module dfl_0 $end
$var wire 1 $ clk $end
$var wire 1 0 in $end
$var wire 1 ( load $end
$var wire 1 (" out $end
$var wire 1 )" _in $end
$scope module df_0 $end
$var wire 1 $ clk $end
$var wire 1 (" out $end
$var wire 1 )" in $end
$var reg 1 (" df_out $end
$upscope $end
$scope module mux2_0 $end
$var wire 1 (" i0 $end
$var wire 1 0 i1 $end
$var wire 1 ( j $end
$var wire 1 )" o $end
$upscope $end
$upscope $end
$scope module dfl_1 $end
$var wire 1 $ clk $end
$var wire 1 *" in $end
$var wire 1 ( load $end
$var wire 1 +" out $end
$var wire 1 ," _in $end
$scope module df_0 $end
$var wire 1 $ clk $end
$var wire 1 +" out $end
$var wire 1 ," in $end
$var reg 1 +" df_out $end
$upscope $end
$scope module mux2_0 $end
$var wire 1 +" i0 $end
$var wire 1 *" i1 $end
$var wire 1 ( j $end
$var wire 1 ," o $end
$upscope $end
$upscope $end
$scope module dfl_2 $end
$var wire 1 $ clk $end
$var wire 1 -" in $end
$var wire 1 ( load $end
$var wire 1 ." out $end
$var wire 1 /" _in $end
$scope module df_0 $end
$var wire 1 $ clk $end
$var wire 1 ." out $end
$var wire 1 /" in $end
$var reg 1 ." df_out $end
$upscope $end
$scope module mux2_0 $end
$var wire 1 ." i0 $end
$var wire 1 -" i1 $end
$var wire 1 ( j $end
$var wire 1 /" o $end
$upscope $end
$upscope $end
$scope module dfl_3 $end
$var wire 1 $ clk $end
$var wire 1 0" in $end
$var wire 1 ( load $end
$var wire 1 1" out $end
$var wire 1 2" _in $end
$scope module df_0 $end
$var wire 1 $ clk $end
$var wire 1 1" out $end
$var wire 1 2" in $end
$var reg 1 1" df_out $end
$upscope $end
$scope module mux2_0 $end
$var wire 1 1" i0 $end
$var wire 1 0" i1 $end
$var wire 1 ( j $end
$var wire 1 2" o $end
$upscope $end
$upscope $end
$scope module dfl_4 $end
$var wire 1 $ clk $end
$var wire 1 3" in $end
$var wire 1 ( load $end
$var wire 1 4" out $end
$var wire 1 5" _in $end
$scope module df_0 $end
$var wire 1 $ clk $end
$var wire 1 4" out $end
$var wire 1 5" in $end
$var reg 1 4" df_out $end
$upscope $end
$scope module mux2_0 $end
$var wire 1 4" i0 $end
$var wire 1 3" i1 $end
$var wire 1 ( j $end
$var wire 1 5" o $end
$upscope $end
$upscope $end
$scope module dfl_5 $end
$var wire 1 $ clk $end
$var wire 1 6" in $end
$var wire 1 ( load $end
$var wire 1 7" out $end
$var wire 1 8" _in $end
$scope module df_0 $end
$var wire 1 $ clk $end
$var wire 1 7" out $end
$var wire 1 8" in $end
$var reg 1 7" df_out $end
$upscope $end
$scope module mux2_0 $end
$var wire 1 7" i0 $end
$var wire 1 6" i1 $end
$var wire 1 ( j $end
$var wire 1 8" o $end
$upscope $end
$upscope $end
$scope module dfl_6 $end
$var wire 1 $ clk $end
$var wire 1 9" in $end
$var wire 1 ( load $end
$var wire 1 :" out $end
$var wire 1 ;" _in $end
$scope module df_0 $end
$var wire 1 $ clk $end
$var wire 1 :" out $end
$var wire 1 ;" in $end
$var reg 1 :" df_out $end
$upscope $end
$scope module mux2_0 $end
$var wire 1 :" i0 $end
$var wire 1 9" i1 $end
$var wire 1 ( j $end
$var wire 1 ;" o $end
$upscope $end
$upscope $end
$scope module dfl_7 $end
$var wire 1 $ clk $end
$var wire 1 <" in $end
$var wire 1 ( load $end
$var wire 1 =" out $end
$var wire 1 >" _in $end
$scope module df_0 $end
$var wire 1 $ clk $end
$var wire 1 =" out $end
$var wire 1 >" in $end
$var reg 1 =" df_out $end
$upscope $end
$scope module mux2_0 $end
$var wire 1 =" i0 $end
$var wire 1 <" i1 $end
$var wire 1 ( j $end
$var wire 1 >" o $end
$upscope $end
$upscope $end
$scope module dfl_8 $end
$var wire 1 $ clk $end
$var wire 1 ?" in $end
$var wire 1 ( load $end
$var wire 1 @" out $end
$var wire 1 A" _in $end
$scope module df_0 $end
$var wire 1 $ clk $end
$var wire 1 @" out $end
$var wire 1 A" in $end
$var reg 1 @" df_out $end
$upscope $end
$scope module mux2_0 $end
$var wire 1 @" i0 $end
$var wire 1 ?" i1 $end
$var wire 1 ( j $end
$var wire 1 A" o $end
$upscope $end
$upscope $end
$scope module muxdf_0 $end
$var wire 1 $ clk $end
$var wire 1 B" i0 $end
$var wire 1 C" i1 $end
$var wire 1 &" load $end
$var wire 1 % s $end
$var wire 1 D" z_ $end
$var wire 1 E" d_in $end
$scope module dfl_0 $end
$var wire 1 $ clk $end
$var wire 1 &" load $end
$var wire 1 D" out $end
$var wire 1 E" in $end
$var wire 1 F" _in $end
$scope module df_0 $end
$var wire 1 $ clk $end
$var wire 1 D" out $end
$var wire 1 F" in $end
$var reg 1 D" df_out $end
$upscope $end
$scope module mux2_0 $end
$var wire 1 D" i0 $end
$var wire 1 &" j $end
$var wire 1 F" o $end
$var wire 1 E" i1 $end
$upscope $end
$upscope $end
$scope module mux2_0 $end
$var wire 1 B" i0 $end
$var wire 1 C" i1 $end
$var wire 1 % j $end
$var wire 1 E" o $end
$upscope $end
$upscope $end
$scope module muxdf_1 $end
$var wire 1 $ clk $end
$var wire 1 G" i0 $end
$var wire 1 H" i1 $end
$var wire 1 &" load $end
$var wire 1 % s $end
$var wire 1 I" z_ $end
$var wire 1 J" d_in $end
$scope module dfl_0 $end
$var wire 1 $ clk $end
$var wire 1 &" load $end
$var wire 1 I" out $end
$var wire 1 J" in $end
$var wire 1 K" _in $end
$scope module df_0 $end
$var wire 1 $ clk $end
$var wire 1 I" out $end
$var wire 1 K" in $end
$var reg 1 I" df_out $end
$upscope $end
$scope module mux2_0 $end
$var wire 1 I" i0 $end
$var wire 1 &" j $end
$var wire 1 K" o $end
$var wire 1 J" i1 $end
$upscope $end
$upscope $end
$scope module mux2_0 $end
$var wire 1 G" i0 $end
$var wire 1 H" i1 $end
$var wire 1 % j $end
$var wire 1 J" o $end
$upscope $end
$upscope $end
$scope module muxdf_2 $end
$var wire 1 $ clk $end
$var wire 1 L" i0 $end
$var wire 1 M" i1 $end
$var wire 1 &" load $end
$var wire 1 % s $end
$var wire 1 N" z_ $end
$var wire 1 O" d_in $end
$scope module dfl_0 $end
$var wire 1 $ clk $end
$var wire 1 &" load $end
$var wire 1 N" out $end
$var wire 1 O" in $end
$var wire 1 P" _in $end
$scope module df_0 $end
$var wire 1 $ clk $end
$var wire 1 N" out $end
$var wire 1 P" in $end
$var reg 1 N" df_out $end
$upscope $end
$scope module mux2_0 $end
$var wire 1 N" i0 $end
$var wire 1 &" j $end
$var wire 1 P" o $end
$var wire 1 O" i1 $end
$upscope $end
$upscope $end
$scope module mux2_0 $end
$var wire 1 L" i0 $end
$var wire 1 M" i1 $end
$var wire 1 % j $end
$var wire 1 O" o $end
$upscope $end
$upscope $end
$scope module muxdf_3 $end
$var wire 1 $ clk $end
$var wire 1 Q" i0 $end
$var wire 1 R" i1 $end
$var wire 1 &" load $end
$var wire 1 % s $end
$var wire 1 S" z_ $end
$var wire 1 T" d_in $end
$scope module dfl_0 $end
$var wire 1 $ clk $end
$var wire 1 &" load $end
$var wire 1 S" out $end
$var wire 1 T" in $end
$var wire 1 U" _in $end
$scope module df_0 $end
$var wire 1 $ clk $end
$var wire 1 S" out $end
$var wire 1 U" in $end
$var reg 1 S" df_out $end
$upscope $end
$scope module mux2_0 $end
$var wire 1 S" i0 $end
$var wire 1 &" j $end
$var wire 1 U" o $end
$var wire 1 T" i1 $end
$upscope $end
$upscope $end
$scope module mux2_0 $end
$var wire 1 Q" i0 $end
$var wire 1 R" i1 $end
$var wire 1 % j $end
$var wire 1 T" o $end
$upscope $end
$upscope $end
$scope module muxdf_4 $end
$var wire 1 $ clk $end
$var wire 1 V" i0 $end
$var wire 1 W" i1 $end
$var wire 1 &" load $end
$var wire 1 % s $end
$var wire 1 X" z_ $end
$var wire 1 Y" d_in $end
$scope module dfl_0 $end
$var wire 1 $ clk $end
$var wire 1 &" load $end
$var wire 1 X" out $end
$var wire 1 Y" in $end
$var wire 1 Z" _in $end
$scope module df_0 $end
$var wire 1 $ clk $end
$var wire 1 X" out $end
$var wire 1 Z" in $end
$var reg 1 X" df_out $end
$upscope $end
$scope module mux2_0 $end
$var wire 1 X" i0 $end
$var wire 1 &" j $end
$var wire 1 Z" o $end
$var wire 1 Y" i1 $end
$upscope $end
$upscope $end
$scope module mux2_0 $end
$var wire 1 V" i0 $end
$var wire 1 W" i1 $end
$var wire 1 % j $end
$var wire 1 Y" o $end
$upscope $end
$upscope $end
$scope module muxdf_5 $end
$var wire 1 $ clk $end
$var wire 1 [" i0 $end
$var wire 1 \" i1 $end
$var wire 1 &" load $end
$var wire 1 % s $end
$var wire 1 ]" z_ $end
$var wire 1 ^" d_in $end
$scope module dfl_0 $end
$var wire 1 $ clk $end
$var wire 1 &" load $end
$var wire 1 ]" out $end
$var wire 1 ^" in $end
$var wire 1 _" _in $end
$scope module df_0 $end
$var wire 1 $ clk $end
$var wire 1 ]" out $end
$var wire 1 _" in $end
$var reg 1 ]" df_out $end
$upscope $end
$scope module mux2_0 $end
$var wire 1 ]" i0 $end
$var wire 1 &" j $end
$var wire 1 _" o $end
$var wire 1 ^" i1 $end
$upscope $end
$upscope $end
$scope module mux2_0 $end
$var wire 1 [" i0 $end
$var wire 1 \" i1 $end
$var wire 1 % j $end
$var wire 1 ^" o $end
$upscope $end
$upscope $end
$scope module muxdf_6 $end
$var wire 1 $ clk $end
$var wire 1 `" i0 $end
$var wire 1 a" i1 $end
$var wire 1 &" load $end
$var wire 1 % s $end
$var wire 1 b" z_ $end
$var wire 1 c" d_in $end
$scope module dfl_0 $end
$var wire 1 $ clk $end
$var wire 1 &" load $end
$var wire 1 b" out $end
$var wire 1 c" in $end
$var wire 1 d" _in $end
$scope module df_0 $end
$var wire 1 $ clk $end
$var wire 1 b" out $end
$var wire 1 d" in $end
$var reg 1 b" df_out $end
$upscope $end
$scope module mux2_0 $end
$var wire 1 b" i0 $end
$var wire 1 &" j $end
$var wire 1 d" o $end
$var wire 1 c" i1 $end
$upscope $end
$upscope $end
$scope module mux2_0 $end
$var wire 1 `" i0 $end
$var wire 1 a" i1 $end
$var wire 1 % j $end
$var wire 1 c" o $end
$upscope $end
$upscope $end
$scope module muxdf_7 $end
$var wire 1 $ clk $end
$var wire 1 e" i0 $end
$var wire 1 f" i1 $end
$var wire 1 &" load $end
$var wire 1 % s $end
$var wire 1 g" z_ $end
$var wire 1 h" d_in $end
$scope module dfl_0 $end
$var wire 1 $ clk $end
$var wire 1 &" load $end
$var wire 1 g" out $end
$var wire 1 h" in $end
$var wire 1 i" _in $end
$scope module df_0 $end
$var wire 1 $ clk $end
$var wire 1 g" out $end
$var wire 1 i" in $end
$var reg 1 g" df_out $end
$upscope $end
$scope module mux2_0 $end
$var wire 1 g" i0 $end
$var wire 1 &" j $end
$var wire 1 i" o $end
$var wire 1 h" i1 $end
$upscope $end
$upscope $end
$scope module mux2_0 $end
$var wire 1 e" i0 $end
$var wire 1 f" i1 $end
$var wire 1 % j $end
$var wire 1 h" o $end
$upscope $end
$upscope $end
$upscope $end
$upscope $end
$upscope $end
$enddefinitions $end
#0
$dumpvars
0i"
0h"
0g"
0f"
0e"
0d"
0c"
0b"
0a"
0`"
0_"
0^"
0]"
0\"
0["
0Z"
0Y"
0X"
0W"
0V"
0U"
0T"
0S"
0R"
0Q"
0P"
0O"
0N"
0M"
0L"
0K"
0J"
0I"
0H"
0G"
0F"
0E"
0D"
0C"
0B"
0A"
0@"
0?"
0>"
0="
0<"
0;"
0:"
09"
08"
07"
06"
05"
04"
03"
02"
01"
00"
0/"
0."
0-"
0,"
0+"
0*"
0)"
0("
b0 '"
0&"
b0 %"
b0 $"
0#"
0""
0!"
0~
0}
0|
0{
0z
0y
0x
0w
0v
0u
0t
0s
0r
0q
0p
0o
0n
0m
0l
0k
0j
b0 i
b0 h
0g
1f
0e
1d
0c
0b
0a
b0 `
b100 _
b0 ^
0]
0\
0[
0Z
0Y
0X
0W
0V
0U
0T
0S
0R
0Q
0P
0O
0N
0M
0L
0K
0J
0I
0H
0G
0F
0E
0D
0C
0B
0A
0@
0?
0>
0=
0<
0;
0:
09
08
07
b0 6
b0 5
b0 4
b0 3
b0 2
b0 1
00
0/
b0 .
b0 -
b0 ,
b0 +
0*
0)
0(
b0 '
b0 &
0%
0$
b0 #
b0 "
b0 !
$end
#10000
1$
#20000
0$
#30000
1$
#40000
0$
#50000
1$
#60000
0$
#70000
1$
#80000
0$
#90000
1$
#100000
1F"
1P"
1U"
1_"
1i"
1g
1E"
1O"
1T"
1^"
1h"
1l
1r
1u
1x
1~
1c
1C"
1M"
1R"
1\"
1f"
1j
1p
1s
1v
1|
1)
1(
1/
1&"
0$
b10110101 #
b10110101 '
b10110101 $"
b1011101 "
b1011101 &
b1011101 h
1%
#110000
1/"
15"
18"
1;"
1A"
1-"
13"
16"
19"
1?"
1X
1N
1I
1D
b1011101 1
b1011101 5
b1011101 %"
1:
1V
1L
1G
1B
18
b1011101 +
b1011101 4
1`"
1V"
1Q"
1G"
b1011010 !
b1011010 .
1b
1g"
1]"
1S"
1N"
b10110101 ,
b10110101 '"
1D"
1}
1w
1t
1q
b1011101 2
b1011101 i
1k
1$
#120000
0$
#125000
0F"
1K"
0P"
1Z"
0_"
1d"
0i"
0C"
0M"
0R"
0\"
0f"
0j
0p
0s
0v
0|
0)
0E"
1J"
0O"
1Y"
0^"
1c"
0h"
b0 #
b0 '
b0 $"
b0 "
b0 &
b0 h
0%
#130000
0/"
05"
0A"
1>"
12"
0-"
03"
0?"
1<"
10"
0X
0N
0:
1?
b101110 1
b101110 5
b101110 %"
1S
1F"
0K"
1P"
0U"
1_"
0d"
1i"
0V
0L
0G
0B
08
1<
1A
1F
1P
1E"
0J"
1O"
0T"
1^"
0c"
1h"
b0 +
b0 4
b101110 3
1B"
0G"
1L"
0Q"
1["
0`"
1e"
b10111010101101 !
b10111010101101 .
1."
14"
17"
1:"
1@"
0D"
1I"
0N"
1X"
0]"
1b"
b101110101011010 ,
b101110101011010 '"
0g"
b1 -
b1 `
1$
#140000
0$
#150000
0>"
1/"
1;"
1M
0<"
1C
1-"
19"
1J
0?
1@
0A"
08"
15"
12"
1X
1R
1D
1H
1>
0?"
06"
13"
10"
1O
1E
b11111 6
1;
0:
0I
1N
b1110100 1
b1110100 5
b1110100 %"
1S
1V
1L
1G
1B
18
0i"
1d"
0Z"
1U"
0P"
1K"
0F"
b1011101 +
b1011101 4
0h"
1c"
0Y"
1T"
0O"
1J"
0E"
17
0F
1K
0P
0e"
1`"
0V"
1Q"
0L"
1G"
0B"
b1011101010110 !
b1011101010110 .
b10111 3
b10 -
b10 `
1g"
0b"
1]"
0S"
1N"
0I"
1D"
0@"
1="
04"
11"
b10111010101101 ,
b10111010101101 '"
0."
1$
#160000
0$
#170000
0/"
0-"
0X
0;"
09"
0R
1>"
0D
18"
15"
1<"
0C
16"
0M
12"
13"
1?
0@
1I
10"
1N
0>
0H
b111010 1
b111010 5
b111010 %"
1S
0W
0O
0;
0E
0J
b0 6
0T
0K"
1P"
0U"
1Z"
0_"
1i"
0V
0L
0G
0B
08
07
0A
1F
1P
0J"
1O"
0T"
1Y"
0^"
1h"
b0 +
b0 4
b111010 3
0G"
1L"
0Q"
1V"
0["
1e"
b11101000101011 !
b11101000101011 .
1."
14"
07"
0="
0D"
1I"
0N"
1S"
0X"
1b"
b111010001010110 ,
b111010001010110 '"
0g"
b11 -
b11 `
1$
#180000
0$
#190000
1/"
1-"
0A"
1>"
0;"
12"
1X
1R
1M
1H
1>
0?"
1<"
09"
10"
1O
1J
1E
b11101 6
1;
0:
1?
0D
b1111010 1
b1111010 5
b1111010 %"
1S
1V
1L
1G
1B
18
0d"
1_"
0Z"
1U"
0P"
b1011101 +
b1011101 4
0c"
1^"
0Y"
1T"
0O"
17
0<
1A
0P
0`"
1["
0V"
1Q"
0L"
b1110100010101 !
b1110100010101 .
b11101 3
b0 -
b0 `
1g"
0]"
1X"
0S"
1N"
0I"
1="
0:"
17"
b11101000101011 ,
b11101000101011 '"
0."
1$
#200000
0$
